README.md
setup.py
pirate_weather/__init__.py
pirate_weather/api.py
pirate_weather/base.py
pirate_weather/exceptions.py
pirate_weather/forecast.py
pirate_weather/request_manager.py
pirate_weather/utils.py
pirate_weather/types/__init__.py
pirate_weather/types/languages.py
pirate_weather/types/units.py
pirate_weather/types/weather.py
pirate_weather_python.egg-info/PKG-INFO
pirate_weather_python.egg-info/SOURCES.txt
pirate_weather_python.egg-info/dependency_links.txt
pirate_weather_python.egg-info/requires.txt
pirate_weather_python.egg-info/top_level.txt
tests/__init__.py
tests/data.py
tests/mokcs.py
tests/test_base.py
tests/test_forecast.py
tests/utils.py