Metadata-Version: 1.1
Name: pirate-weather-python
Version: 0.0.6
Summary: The Pirate Weather API wrapper
Home-page: https://github.com/bakobako/pirate-weather-python
Author: bakobako
Author-email: adam.bako@keboola.com
License: GPLv3 License
Download-URL: https://github.com/bakobako/pirate-weather-python/archive/0.0.6.tar.gz
Platform: UNKNOWN
Classifier: Environment :: Web Environment
Classifier: Intended Audience :: Developers
Classifier: License :: OSI Approved :: MIT License
Classifier: Programming Language :: Python :: 3.6
Classifier: Topic :: Software Development :: Libraries :: Python Modules
